puffbird/__init__.py
puffbird/callables.py
puffbird/err.py
puffbird/frame.py
puffbird/shortcuts.py
puffbird/utils.py
puffbird-0.0.1.dist-info/LICENSE
puffbird-0.0.1.dist-info/METADATA
puffbird-0.0.1.dist-info/WHEEL
puffbird-0.0.1.dist-info/top_level.txt
puffbird-0.0.1.dist-info/RECORD
